<score-partwise><measure number="1">
      <attributes>
        <divisions>480</divisions>
        <key>
          <fifths>-5</fifths>
          </key>
        <time>
          <beats>4</beats>
          <beat-type>4</beat-type>
          </time>
        <staves>2</staves>
        <clef number="1">
          <sign>G</sign>
          <line>2</line>
          </clef>
        <clef number="2">
          <sign>F</sign>
          <line>4</line>
          </clef>
        </attributes>
      <note dynamics="56.67">
        <pitch>
          <step>D</step>
          <alter>-1</alter>
          <octave>4</octave>
          </pitch>
        <duration>960</duration>
        <voice>1</voice>
        <type>half</type>
        <stem>up</stem>
        <staff>1</staff>
        </note>
      <note dynamics="66.67">
        <chord />
        <pitch>
          <step>F</step>
          <alter>-1</alter>
          <octave>4</octave>
          </pitch>
        <duration>960</duration>
        <voice>1</voice>
        <type>half</type>
        <accidental>flat</accidental>
        <stem>up</stem>
        <staff>1</staff>
        </note>
      <note dynamics="76.67">
        <chord />
        <pitch>
          <step>B</step>
          <alter>-1</alter>
          <octave>4</octave>
          </pitch>
        <duration>960</duration>
        <voice>1</voice>
        <type>half</type>
        <stem>up</stem>
        <staff>1</staff>
        </note>
      <note dynamics="55.56">
        <pitch>
          <step>C</step>
          <octave>4</octave>
          </pitch>
        <duration>480</duration>
        <voice>1</voice>
        <type>quarter</type>
        <stem>up</stem>
        <staff>1</staff>
        </note>
      <note dynamics="63.33">
        <chord />
        <pitch>
          <step>E</step>
          <alter>-1</alter>
          <octave>4</octave>
          </pitch>
        <duration>480</duration>
        <voice>1</voice>
        <type>quarter</type>
        <stem>up</stem>
        <staff>1</staff>
        </note>
      <note dynamics="75.56">
        <chord />
        <pitch>
          <step>A</step>
          <alter>-1</alter>
          <octave>4</octave>
          </pitch>
        <duration>480</duration>
        <voice>1</voice>
        <type>quarter</type>
        <stem>up</stem>
        <staff>1</staff>
        </note>
      <note dynamics="52.22">
        <pitch>
          <step>D</step>
          <alter>-1</alter>
          <octave>4</octave>
          </pitch>
        <duration>480</duration>
        <voice>1</voice>
        <type>quarter</type>
        <stem>up</stem>
        <staff>1</staff>
        </note>
      <note dynamics="62.22">
        <chord />
        <pitch>
          <step>F</step>
          <alter>-1</alter>
          <octave>4</octave>
          </pitch>
        <duration>480</duration>
        <voice>1</voice>
        <type>quarter</type>
        <stem>up</stem>
        <staff>1</staff>
        </note>
      <note dynamics="74.44">
        <chord />
        <pitch>
          <step>B</step>
          <alter>-1</alter>
          <octave>4</octave>
          </pitch>
        <duration>480</duration>
        <voice>1</voice>
        <type>quarter</type>
        <stem>up</stem>
        <staff>1</staff>
        </note>
      <backup>
        <duration>1920</duration>
        </backup>
      <note dynamics="55.56">
        <pitch>
          <step>A</step>
          <alter>-1</alter>
          <octave>3</octave>
          </pitch>
        <duration>240</duration>
        <voice>2</voice>
        <type>eighth</type>
        <stem>down</stem>
        <staff>1</staff>
        <beam number="1">begin</beam>
        </note>
      <note dynamics="55.56">
        <pitch>
          <step>A</step>
          <alter>-1</alter>
          <octave>3</octave>
          </pitch>
        <duration>240</duration>
        <voice>2</voice>
        <type>eighth</type>
        <stem>down</stem>
        <staff>1</staff>
        <beam number="1">continue</beam>
        </note>
      <note dynamics="53.33">
        <pitch>
          <step>A</step>
          <alter>-1</alter>
          <octave>3</octave>
          </pitch>
        <duration>240</duration>
        <voice>2</voice>
        <type>eighth</type>
        <stem>down</stem>
        <staff>1</staff>
        <beam number="1">continue</beam>
        </note>
      <note dynamics="53.33">
        <pitch>
          <step>A</step>
          <alter>-1</alter>
          <octave>3</octave>
          </pitch>
        <duration>240</duration>
        <voice>2</voice>
        <type>eighth</type>
        <stem>down</stem>
        <staff>1</staff>
        <beam number="1">end</beam>
        </note>
      <note dynamics="52.22">
        <pitch>
          <step>A</step>
          <alter>-1</alter>
          <octave>3</octave>
          </pitch>
        <duration>240</duration>
        <voice>2</voice>
        <type>eighth</type>
        <stem>down</stem>
        <staff>1</staff>
        <beam number="1">begin</beam>
        </note>
      <note dynamics="52.22">
        <pitch>
          <step>A</step>
          <alter>-1</alter>
          <octave>3</octave>
          </pitch>
        <duration>240</duration>
        <voice>2</voice>
        <type>eighth</type>
        <stem>down</stem>
        <staff>1</staff>
        <beam number="1">continue</beam>
        </note>
      <note dynamics="52.22">
        <pitch>
          <step>A</step>
          <alter>-1</alter>
          <octave>3</octave>
          </pitch>
        <duration>240</duration>
        <voice>2</voice>
        <type>eighth</type>
        <stem>down</stem>
        <staff>1</staff>
        <beam number="1">continue</beam>
        </note>
      <note dynamics="51.11">
        <pitch>
          <step>A</step>
          <alter>-1</alter>
          <octave>3</octave>
          </pitch>
        <duration>240</duration>
        <voice>2</voice>
        <type>eighth</type>
        <stem>down</stem>
        <staff>1</staff>
        <beam number="1">end</beam>
        </note>
      <backup>
        <duration>1920</duration>
        </backup>
      <note dynamics="46.67">
        <pitch>
          <step>A</step>
          <alter>-1</alter>
          <octave>1</octave>
          </pitch>
        <duration>1440</duration>
        <voice>5</voice>
        <type>half</type>
        <dot />
        <stem>up</stem>
        <staff>2</staff>
        </note>
      <note dynamics="61.11">
        <chord />
        <pitch>
          <step>A</step>
          <alter>-1</alter>
          <octave>2</octave>
          </pitch>
        <duration>1440</duration>
        <voice>5</voice>
        <type>half</type>
        <dot />
        <stem>up</stem>
        <staff>2</staff>
        </note>
      <note dynamics="51.11">
        <pitch>
          <step>D</step>
          <alter>-1</alter>
          <octave>2</octave>
          </pitch>
        <duration>480</duration>
        <voice>5</voice>
        <type>quarter</type>
        <stem>up</stem>
        <staff>2</staff>
        </note>
      <note dynamics="66.67">
        <chord />
        <pitch>
          <step>A</step>
          <alter>-1</alter>
          <octave>2</octave>
          </pitch>
        <duration>480</duration>
        <voice>5</voice>
        <type>quarter</type>
        <stem>up</stem>
        <staff>2</staff>
        </note>
      </measure>
    <measure number="2">
      <note dynamics="52.22">
        <pitch>
          <step>D</step>
          <alter>-1</alter>
          <octave>4</octave>
          </pitch>
        <duration>960</duration>
        <voice>1</voice>
        <type>half</type>
        <stem>up</stem>
        <staff>1</staff>
        </note>
      <note dynamics="62.22">
        <chord />
        <pitch>
          <step>F</step>
          <alter>-1</alter>
          <octave>4</octave>
          </pitch>
        <duration>960</duration>
        <voice>1</voice>
        <type>half</type>
        <accidental>flat</accidental>
        <stem>up</stem>
        <staff>1</staff>
        </note>
      <note dynamics="74.44">
        <chord />
        <pitch>
          <step>B</step>
          <alter>-1</alter>
          <octave>4</octave>
          </pitch>
        <duration>960</duration>
        <voice>1</voice>
        <type>half</type>
        <stem>up</stem>
        <staff>1</staff>
        </note>
      <note dynamics="48.89">
        <pitch>
          <step>C</step>
          <octave>4</octave>
          </pitch>
        <duration>480</duration>
        <voice>1</voice>
        <type>quarter</type>
        <stem>up</stem>
        <staff>1</staff>
        </note>
      <note dynamics="55.56">
        <chord />
        <pitch>
          <step>E</step>
          <alter>-1</alter>
          <octave>4</octave>
          </pitch>
        <duration>480</duration>
        <voice>1</voice>
        <type>quarter</type>
        <stem>up</stem>
        <staff>1</staff>
        </note>
      <note dynamics="66.67">
        <chord />
        <pitch>
          <step>A</step>
          <alter>-1</alter>
          <octave>4</octave>
          </pitch>
        <duration>480</duration>
        <voice>1</voice>
        <type>quarter</type>
        <stem>up</stem>
        <staff>1</staff>
        </note>
      <note dynamics="53.33">
        <pitch>
          <step>D</step>
          <alter>-1</alter>
          <octave>4</octave>
          </pitch>
        <duration>480</duration>
        <voice>1</voice>
        <type>quarter</type>
        <stem>up</stem>
        <staff>1</staff>
        </note>
      <note dynamics="53.33">
        <chord />
        <pitch>
          <step>F</step>
          <alter>-1</alter>
          <octave>4</octave>
          </pitch>
        <duration>480</duration>
        <voice>1</voice>
        <type>quarter</type>
        <stem>up</stem>
        <staff>1</staff>
        </note>
      <note dynamics="63.33">
        <chord />
        <pitch>
          <step>B</step>
          <alter>-1</alter>
          <octave>4</octave>
          </pitch>
        <duration>480</duration>
        <voice>1</voice>
        <type>quarter</type>
        <stem>up</stem>
        <staff>1</staff>
        </note>
      <backup>
        <duration>1920</duration>
        </backup>
      <note dynamics="52.22">
        <pitch>
          <step>A</step>
          <alter>-1</alter>
          <octave>3</octave>
          </pitch>
        <duration>240</duration>
        <voice>2</voice>
        <type>eighth</type>
        <stem>down</stem>
        <staff>1</staff>
        <beam number="1">begin</beam>
        </note>
      <note dynamics="51.11">
        <pitch>
          <step>A</step>
          <alter>-1</alter>
          <octave>3</octave>
          </pitch>
        <duration>240</duration>
        <voice>2</voice>
        <type>eighth</type>
        <stem>down</stem>
        <staff>1</staff>
        <beam number="1">continue</beam>
        </note>
      <note dynamics="48.89">
        <pitch>
          <step>A</step>
          <alter>-1</alter>
          <octave>3</octave>
          </pitch>
        <duration>240</duration>
        <voice>2</voice>
        <type>eighth</type>
        <stem>down</stem>
        <staff>1</staff>
        <beam number="1">continue</beam>
        </note>
      <note dynamics="46.67">
        <pitch>
          <step>A</step>
          <alter>-1</alter>
          <octave>3</octave>
          </pitch>
        <duration>240</duration>
        <voice>2</voice>
        <type>eighth</type>
        <stem>down</stem>
        <staff>1</staff>
        <beam number="1">end</beam>
        </note>
      <note dynamics="45.56">
        <pitch>
          <step>A</step>
          <alter>-1</alter>
          <octave>3</octave>
          </pitch>
        <duration>240</duration>
        <voice>2</voice>
        <type>eighth</type>
        <stem>down</stem>
        <staff>1</staff>
        <beam number="1">begin</beam>
        </note>
      <note dynamics="44.44">
        <pitch>
          <step>A</step>
          <alter>-1</alter>
          <octave>3</octave>
          </pitch>
        <duration>240</duration>
        <voice>2</voice>
        <type>eighth</type>
        <stem>down</stem>
        <staff>1</staff>
        <beam number="1">continue</beam>
        </note>
      <note dynamics="43.33">
        <pitch>
          <step>A</step>
          <alter>-1</alter>
          <octave>3</octave>
          </pitch>
        <duration>240</duration>
        <voice>2</voice>
        <type>eighth</type>
        <stem>down</stem>
        <staff>1</staff>
        <beam number="1">continue</beam>
        </note>
      <note dynamics="43.33">
        <pitch>
          <step>A</step>
          <alter>-1</alter>
          <octave>3</octave>
          </pitch>
        <duration>240</duration>
        <voice>2</voice>
        <type>eighth</type>
        <stem>down</stem>
        <staff>1</staff>
        <beam number="1">end</beam>
        </note>
      <backup>
        <duration>1920</duration>
        </backup>
      <note dynamics="46.67">
        <pitch>
          <step>A</step>
          <alter>-1</alter>
          <octave>1</octave>
          </pitch>
        <duration>1440</duration>
        <voice>5</voice>
        <type>half</type>
        <dot />
        <stem>up</stem>
        <staff>2</staff>
        </note>
      <note dynamics="55.56">
        <chord />
        <pitch>
          <step>A</step>
          <alter>-1</alter>
          <octave>2</octave>
          </pitch>
        <duration>1440</duration>
        <voice>5</voice>
        <type>half</type>
        <dot />
        <stem>up</stem>
        <staff>2</staff>
        </note>
      <note dynamics="46.67">
        <pitch>
          <step>D</step>
          <alter>-1</alter>
          <octave>2</octave>
          </pitch>
        <duration>480</duration>
        <voice>5</voice>
        <type>quarter</type>
        <stem>up</stem>
        <staff>2</staff>
        </note>
      <note dynamics="56.67">
        <chord />
        <pitch>
          <step>A</step>
          <alter>-1</alter>
          <octave>2</octave>
          </pitch>
        <duration>480</duration>
        <voice>5</voice>
        <type>quarter</type>
        <stem>up</stem>
        <staff>2</staff>
        </note>
      </measure>
    <measure number="3">
      <note>
        <rest />
        <duration>1920</duration>
        <voice>1</voice>
        <staff>1</staff>
        </note>
      <backup>
        <duration>1920</duration>
        </backup>
      <note>
        <pitch>
          <step>A</step>
          <alter>-1</alter>
          <octave>3</octave>
          </pitch>
        <duration>240</duration>
        <voice>2</voice>
        <type>eighth</type>
        <stem>down</stem>
        <staff>1</staff>
        <beam number="1">begin</beam>
        </note>
      <note>
        <chord />
        <pitch>
          <step>D</step>
          <alter>-1</alter>
          <octave>4</octave>
          </pitch>
        <duration>240</duration>
        <voice>2</voice>
        <type>eighth</type>
        <stem>down</stem>
        <staff>1</staff>
        </note>
      <note>
        <chord />
        <pitch>
          <step>F</step>
          <alter>-1</alter>
          <octave>4</octave>
          </pitch>
        <duration>240</duration>
        <voice>2</voice>
        <type>eighth</type>
        <accidental>flat</accidental>
        <stem>down</stem>
        <staff>1</staff>
        </note>
      <note>
        <chord />
        <pitch>
          <step>B</step>
          <alter>-1</alter>
          <octave>4</octave>
          </pitch>
        <duration>240</duration>
        <voice>2</voice>
        <type>eighth</type>
        <stem>down</stem>
        <staff>1</staff>
        </note>
      <note>
        <pitch>
          <step>A</step>
          <alter>-1</alter>
          <octave>3</octave>
          </pitch>
        <duration>240</duration>
        <voice>2</voice>
        <type>eighth</type>
        <stem>down</stem>
        <staff>1</staff>
        <beam number="1">continue</beam>
        </note>
      <note>
        <pitch>
          <step>A</step>
          <alter>-1</alter>
          <octave>3</octave>
          </pitch>
        <duration>240</duration>
        <voice>2</voice>
        <type>eighth</type>
        <stem>down</stem>
        <staff>1</staff>
        <beam number="1">continue</beam>
        </note>
      <note>
        <chord />
        <pitch>
          <step>C</step>
          <octave>4</octave>
          </pitch>
        <duration>240</duration>
        <voice>2</voice>
        <type>eighth</type>
        <stem>down</stem>
        <staff>1</staff>
        </note>
      <note>
        <chord />
        <pitch>
          <step>E</step>
          <alter>-1</alter>
          <octave>4</octave>
          </pitch>
        <duration>240</duration>
        <voice>2</voice>
        <type>eighth</type>
        <stem>down</stem>
        <staff>1</staff>
        </note>
      <note>
        <chord />
        <pitch>
          <step>A</step>
          <alter>-1</alter>
          <octave>4</octave>
          </pitch>
        <duration>240</duration>
        <voice>2</voice>
        <type>eighth</type>
        <stem>down</stem>
        <staff>1</staff>
        </note>
      <note>
        <pitch>
          <step>A</step>
          <alter>-1</alter>
          <octave>3</octave>
          </pitch>
        <duration>240</duration>
        <voice>2</voice>
        <type>eighth</type>
        <stem>down</stem>
        <staff>1</staff>
        <beam number="1">end</beam>
        </note>
      <note>
        <pitch>
          <step>A</step>
          <alter>-1</alter>
          <octave>3</octave>
          </pitch>
        <duration>240</duration>
        <voice>2</voice>
        <type>eighth</type>
        <stem>down</stem>
        <staff>1</staff>
        <beam number="1">begin</beam>
        </note>
      <note>
        <pitch>
          <step>A</step>
          <alter>-1</alter>
          <octave>3</octave>
          </pitch>
        <duration>240</duration>
        <voice>2</voice>
        <type>eighth</type>
        <stem>down</stem>
        <staff>1</staff>
        <beam number="1">continue</beam>
        </note>
      <note>
        <pitch>
          <step>A</step>
          <alter>-1</alter>
          <octave>3</octave>
          </pitch>
        <duration>240</duration>
        <voice>2</voice>
        <type>eighth</type>
        <stem>down</stem>
        <staff>1</staff>
        <beam number="1">continue</beam>
        </note>
      <note>
        <pitch>
          <step>A</step>
          <alter>-1</alter>
          <octave>3</octave>
          </pitch>
        <duration>240</duration>
        <voice>2</voice>
        <type>eighth</type>
        <stem>down</stem>
        <staff>1</staff>
        <beam number="1">end</beam>
        </note>
      <backup>
        <duration>1920</duration>
        </backup>
      <note>
        <rest />
        <duration>1920</duration>
        <voice>5</voice>
        <staff>2</staff>
        </note>
      <backup>
        <duration>1920</duration>
        </backup>
      <note>
        <pitch>
          <step>A</step>
          <alter>-1</alter>
          <octave>1</octave>
          </pitch>
        <duration>480</duration>
        <voice>6</voice>
        <type>quarter</type>
        <stem>down</stem>
        <staff>2</staff>
        </note>
      <note>
        <chord />
        <pitch>
          <step>A</step>
          <alter>-1</alter>
          <octave>2</octave>
          </pitch>
        <duration>480</duration>
        <voice>6</voice>
        <type>quarter</type>
        <stem>down</stem>
        <staff>2</staff>
        </note>
      <note>
        <pitch>
          <step>A</step>
          <alter>-1</alter>
          <octave>2</octave>
          </pitch>
        <duration>480</duration>
        <voice>6</voice>
        <type>quarter</type>
        <stem>down</stem>
        <staff>2</staff>
        </note>
      <note>
        <rest />
        <duration>240</duration>
        <voice>6</voice>
        <type>eighth</type>
        <staff>2</staff>
        </note>
      <note>
        <pitch>
          <step>F</step>
          <octave>3</octave>
          </pitch>
        <duration>240</duration>
        <voice>6</voice>
        <type>eighth</type>
        <stem>down</stem>
        <staff>2</staff>
        <beam number="1">begin</beam>
        </note>
      <note>
        <pitch>
          <step>G</step>
          <alter>-1</alter>
          <octave>3</octave>
          </pitch>
        <duration>240</duration>
        <voice>6</voice>
        <type>eighth</type>
        <stem>down</stem>
        <staff>2</staff>
        <beam number="1">continue</beam>
        </note>
      <note>
        <pitch>
          <step>E</step>
          <alter>-1</alter>
          <octave>3</octave>
          </pitch>
        <duration>240</duration>
        <voice>6</voice>
        <type>eighth</type>
        <stem>down</stem>
        <staff>2</staff>
        <beam number="1">end</beam>
        </note>
      </measure>
    <measure number="4">
      <note dynamics="58.89">
        <pitch>
          <step>F</step>
          <octave>5</octave>
          </pitch>
        <duration>360</duration>
        <voice>1</voice>
        <type>eighth</type>
        <dot />
        <stem>down</stem>
        <staff>1</staff>
        <beam number="1">begin</beam>
        </note>
      <note dynamics="50.00">
        <pitch>
          <step>D</step>
          <alter>-1</alter>
          <octave>5</octave>
          </pitch>
        <duration>120</duration>
        <voice>1</voice>
        <type>16th</type>
        <stem>down</stem>
        <staff>1</staff>
        <beam number="1">end</beam>
        <beam number="2">backward hook</beam>
        </note>
      <note dynamics="56.67">
        <pitch>
          <step>A</step>
          <alter>-1</alter>
          <octave>4</octave>
          </pitch>
        <duration>960</duration>
        <voice>1</voice>
        <type>half</type>
        <stem>up</stem>
        <staff>1</staff>
        </note>
      <note dynamics="55.56">
        <pitch>
          <step>B</step>
          <alter>-1</alter>
          <octave>4</octave>
          </pitch>
        <duration>480</duration>
        <voice>1</voice>
        <type>quarter</type>
        <stem>down</stem>
        <staff>1</staff>
        </note>
      <backup>
        <duration>1920</duration>
        </backup>
      <note dynamics="38.89">
        <pitch>
          <step>D</step>
          <alter>-1</alter>
          <octave>3</octave>
          </pitch>
        <duration>240</duration>
        <voice>5</voice>
        <type>eighth</type>
        <stem>down</stem>
        <staff>2</staff>
        <beam number="1">begin</beam>
        </note>
      <note dynamics="33.33">
        <pitch>
          <step>A</step>
          <alter>-1</alter>
          <octave>3</octave>
          </pitch>
        <duration>240</duration>
        <voice>5</voice>
        <type>eighth</type>
        <stem>down</stem>
        <staff>2</staff>
        <beam number="1">continue</beam>
        </note>
      <note dynamics="18.89">
        <pitch>
          <step>D</step>
          <alter>-1</alter>
          <octave>4</octave>
          </pitch>
        <duration>240</duration>
        <voice>5</voice>
        <type>eighth</type>
        <stem>down</stem>
        <staff>2</staff>
        <beam number="1">continue</beam>
        </note>
      <note dynamics="28.89">
        <chord />
        <pitch>
          <step>F</step>
          <octave>4</octave>
          </pitch>
        <duration>240</duration>
        <voice>5</voice>
        <type>eighth</type>
        <stem>down</stem>
        <staff>2</staff>
        </note>
      <note dynamics="21.11">
        <pitch>
          <step>A</step>
          <alter>-1</alter>
          <octave>3</octave>
          </pitch>
        <duration>240</duration>
        <voice>5</voice>
        <type>eighth</type>
        <stem>down</stem>
        <staff>2</staff>
        <beam number="1">end</beam>
        </note>
      <note dynamics="25.56">
        <pitch>
          <step>A</step>
          <alter>-1</alter>
          <octave>3</octave>
          </pitch>
        <duration>240</duration>
        <voice>5</voice>
        <type>eighth</type>
        <stem>down</stem>
        <staff>2</staff>
        <beam number="1">begin</beam>
        </note>
      <note dynamics="21.11">
        <pitch>
          <step>A</step>
          <alter>-1</alter>
          <octave>3</octave>
          </pitch>
        <duration>240</duration>
        <voice>5</voice>
        <type>eighth</type>
        <stem>down</stem>
        <staff>2</staff>
        <beam number="1">continue</beam>
        </note>
      <note dynamics="30.00">
        <pitch>
          <step>A</step>
          <alter>-1</alter>
          <octave>3</octave>
          </pitch>
        <duration>240</duration>
        <voice>5</voice>
        <type>eighth</type>
        <stem>down</stem>
        <staff>2</staff>
        <beam number="1">continue</beam>
        </note>
      <note dynamics="31.11">
        <pitch>
          <step>A</step>
          <alter>-1</alter>
          <octave>3</octave>
          </pitch>
        <duration>240</duration>
        <voice>5</voice>
        <type>eighth</type>
        <stem>down</stem>
        <staff>2</staff>
        <beam number="1">end</beam>
        </note>
      </measure>
    </score-partwise>